fastbacktest/__init__.py
fastbacktest-0.0.1.dist-info/METADATA
fastbacktest-0.0.1.dist-info/WHEEL
fastbacktest-0.0.1.dist-info/RECORD
